testmynb/__init__.py
testmynb/__main__.py
testmynb/_ansi.py
testmynb/handler.py
testmynb/magic.py
testmynb/main.py
testmynb/notebook.py
testmynb-0.0.1.dist-info/AUTHORS.rst
testmynb-0.0.1.dist-info/LICENSE
testmynb-0.0.1.dist-info/METADATA
testmynb-0.0.1.dist-info/WHEEL
testmynb-0.0.1.dist-info/entry_points.txt
testmynb-0.0.1.dist-info/top_level.txt
testmynb-0.0.1.dist-info/RECORD
